{
  "מיקומים גאוגרפיים": {
    "קל": [
      "ישראל",
      "ירושלים",
      "ארצות הברית",
      "ניו יורק",
      "פריז",
      "צרפת",
      "לונדון",
      "אנגליה",
      "ים המלח",
      "הכנרת",
      "אילת",
      "תל אביב",
      "אפריקה",
      "אירופה",
      "אסיה",
      "אנטארקטיקה",
      "אוסטרליה",
      "איטליה",
      "רומא",
      "ספרד",
      "ברצלונה",
      "מדריד",
      "ברזיל",
      "ארגנטינה",
      "הר האוורסט",
      "יפן",
      "טוקיו",
      "סין",
      "הים התיכון",
      "הים האדום",
      "חיפה",
      "ים סוף",
      "נגב",
      "יער האמזונס",
      "מדבר סהרה",
      "קנדה",
      "רוסיה",
      "מוסקבה",
      "הודו",
      "אוקיינוס",
      "אי",
      "יבשת",
      "הר",
      "עמק",
      "נהר",
      "אגם",
      "מצרים",
      "הפירמידות",
      "יוון",
      "אתונה"
    ],
    "בינוני": [
      "מקסיקו",
      "קובה",
      "תאילנד",
      "בנגקוק",
      "נורווגיה",
      "אוסלו",
      "ברלין",
      "גרמניה",
      "אמסטרדם",
      "הולנד",
      "שוויץ",
      "הרי האלפים",
      "טורקיה",
      "איסטנבול",
      "קפריסין",
      "דובאי",
      "איחוד האמירויות",
      "ניו זילנד",
      "הוואי",
      "אלסקה",
      "קליפורניה",
      "לאס וגאס",
      "מיאמי",
      "לוס אנג'לס",
      "האוקיינוס השקט",
      "האוקיינוס האטלנטי",
      "נהר הנילוס",
      "נהר הירדן",
      "הרי ההימלאיה",
      "מרוקו",
      "דרום אפריקה",
      "קניה",
      "ויאטנם",
      "פיליפינים",
      "קוריאה הדרומית",
      "סיאול",
      "דבלין",
      "אירלנד",
      "סקוטלנד",
      "מונטריאול",
      "טורונטו",
      "פרו",
      "מאצ'ו פיצ'ו",
      "צ'ילה",
      "קולומביה",
      "פורטוגל",
      "ליסבון",
      "פראג",
      "צ'כיה",
      "בודפשט"
    ],
    "קשה": [
      "מדגסקר",
      "איסלנד",
      "גרינלנד",
      "סרי לנקה",
      "הרי האנדים",
      "נהר האמזונס",
      "אגן הקונגו",
      "מדבר גובי",
      "פטגוניה",
      "טסמניה",
      "איי גלאפגוס",
      "פיג'י",
      "מלדיביים",
      "קו המשווה",
      "חוג הסרטן",
      "הקוטב הצפוני",
      "הקוטב הדרומי",
      "אוקיינוס ההודי",
      "מצר גיברלטר",
      "תעלת סואץ",
      "תעלת פנמה",
      "הים הכספי",
      "הים השחור",
      "ימת אראל",
      "אגם ויקטוריה",
      "מפלי הניאגרה",
      "מפלי איגואסו",
      "הר קילימנג'רו",
      "מון בלאן",
      "הר פוג'י",
      "רכס הקווקז",
      "סיביר",
      "טיבט",
      "מונגוליה",
      "נפאל",
      "בהוטן",
      "אינדונזיה",
      "ג'קרטה",
      "פפואה גינאה החדשה",
      "בוליביה",
      "אורוגוואי",
      "ונצואלה",
      "אקוודור",
      "סנגל",
      "אתיופיה",
      "ניגריה",
      "זימבבואה",
      "אוזבקיסטן",
      "קזחסטן",
      "אפגניסטן"
    ]
  },
  "חיות": {
    "קל": [
      "כלב",
      "חתול",
      "אריה",
      "נמר",
      "פיל",
      "קוף",
      "סוס",
      "פרה",
      "כבשה",
      "עז",
      "חזיר",
      "תרנגול",
      "ברווז",
      "אווז",
      "ציפור",
      "דג",
      "נחש",
      "צפרדע",
      "עכבר",
      "חולדה",
      "ארנב",
      "צב",
      "דוב",
      "זאב",
      "שועל",
      "גמל",
      "חמור",
      "פנדה",
      "ג'ירפה",
      "זברה",
      "היפופוטם",
      "תנין",
      "פינגווין",
      "ינשוף",
      "נשר",
      "יונה",
      "עטלף",
      "נמלה",
      "זבוב",
      "יתוש",
      "דבורה",
      "פרפר",
      "עכביש",
      "ג'וק",
      "שבלול",
      "תולעת",
      "דולפין",
      "לוויתן",
      "כריש",
      "סרטן"
    ],
    "בינוני": [
      "קרנף",
      "תמנון",
      "דיונון",
      "יען",
      "טווס",
      "פלמינגו",
      "ברבור",
      "חסידה",
      "שקנאי",
      "צבי",
      "אייל",
      "יחמור",
      "שור",
      "איל",
      "אלמנה שחורה",
      "טרנטולה",
      "סוס ים",
      "טוקן",
      "תנשמת",
      "עורב",
      "בז",
      "עיט",
      "לטאה",
      "זיקית",
      "איגואנה",
      "סלמנדרה",
      "קרפדה",
      "תן",
      "צבוע",
      "ברדלס",
      "פומה",
      "יגואר",
      "טיגריס",
      "דוב קוטב",
      "דוב נמלים",
      "עצלן",
      "קנגורו",
      "קואלה",
      "חוגלה",
      "קיפוד",
      "דורבן",
      "חולד",
      "סנאי",
      "אוגר",
      "שרקן",
      "צ'ינצ'ילה",
      "חמוס",
      "בונה",
      "כלב ים",
      "ניבתן"
    ],
    "קשה": [
      "קפיברה",
      "שנבוב",
      "פנגולין",
      "טפיר",
      "בבון",
      "מנדריל",
      "למור",
      "אורנגוטן",
      "גיבון",
      "שימפנזה",
      "גורילה",
      "מקוק",
      "סוריקטה",
      "נמיה",
      "גירית",
      "לוטרה",
      "חורפן",
      "סמור",
      "פנק",
      "קויוט",
      "דינגו",
      "זאב טסמני",
      "שד טסמני",
      "וומבט",
      "פוסום",
      "וולבי",
      "אמו",
      "קזואר",
      "קיווי",
      "ברווזן",
      "אכידנה",
      "אלפקה",
      "לאמה",
      "ויקוניה",
      "גואנקו",
      "יאק",
      "תאו",
      "ביזון",
      "אנטילופה",
      "גנו",
      "אימפלה",
      "ראם",
      "יעל",
      "מופלון",
      "טהר",
      "קודו",
      "בונגו",
      "אוקפי",
      "פודו",
      "דיק דיק"
    ]
  },
  "עולם חיל האוויר": {
    "קל": [
      "מטוס",
      "מסוק",
      "טייס",
      "שמיים",
      "ענן",
      "שדה תעופה",
      "כנפיים",
      "המראה",
      "נחיתה",
      "אוויר",
      "טייסת",
      "בסיס",
      "מדים",
      "רדאר",
      "חיל האוויר",
      "צנחן",
      "מצנח",
      "קסדה",
      "אוזניות",
      "מגדל פיקוח",
      "כוננות",
      "פצצה",
      "טיל",
      "מטרה",
      "טיסה",
      "קרב",
      "מטוס קרב",
      "נוסע",
      "צוות",
      "מנוע",
      "אווירון",
      "דלק",
      "מסלול",
      "סירנה",
      "יירוט",
      "קוקפיט",
      "מפקד",
      "חייל",
      "צבא",
      "כלי טיס",
      "חלל",
      "להק",
      "תדלוק",
      "זנב",
      "כנף",
      "גלגלים",
      "שחקים",
      "מדחף",
      "סילון",
      "אזעקה"
    ],
    "בינוני": [
      "נווט",
      "מכונאי",
      "פקח טיסה",
      "טכנאי",
      "כיסא מפלט",
      "חופה",
      "הגנה אווירית",
      "נ\"מ",
      "מל\"ט",
      "כטב\"ם",
      "רחפן",
      "כיפת ברזל",
      "מטוס תובלה",
      "מיראז'",
      "גיחה",
      "מבנה",
      "מכ\"ם",
      "בום על קולי",
      "מהירות הקול",
      "אף-16",
      "אף-15",
      "תדלוק אווירי",
      "פצצת תאורה",
      "מוץ",
      "נור",
      "אות קריאה",
      "סחרור",
      "כוח ג'י",
      "חליפת לחץ",
      "סימולטור",
      "פטריוט",
      "סוללה",
      "חץ",
      "קלע דוד",
      "דת\"ק",
      "לוחמה אלקטרונית",
      "טייס משנה",
      "טייסת חילוץ",
      "כנפי טיס",
      "תחקיר",
      "תדריך",
      "הפצצה",
      "מטוס ללא טייס",
      "מטאורולוגיה",
      "קורס טיס",
      "קצין",
      "נגד",
      "מוסך",
      "האנגר",
      "אווירובטיקה"
    ],
    "קשה": [
      "אדיר",
      "סופה",
      "רעם",
      "ברק",
      "בז",
      "יסעור",
      "פתן",
      "שרף",
      "צופית",
      "עטלף",
      "נחשון",
      "קרנף",
      "שמשון",
      "איתן",
      "זיק",
      "שובל",
      "כוכב",
      "ל\"א",
      "שלדג",
      "יחידה 669",
      "חצרים",
      "תל נוף",
      "רמת דוד",
      "נבטים",
      "חצור",
      "עובדה",
      "פלמחים",
      "רמון",
      "יב\"א",
      "פקמ\"צית",
      "בקר טיסה",
      "ורטיגו",
      "זווית התקפה",
      "מספר מאך",
      "אוויוניקה",
      "טיל אוויר-אוויר",
      "טיל אוויר-קרקע",
      "פוד תקיפה",
      "טיל פופאי",
      "תעשייה אווירית",
      "מבצע אופרה",
      "רוטור",
      "עלרוד",
      "גלגול",
      "סבסוב",
      "חימוש מונחה",
      "פנטום",
      "עיטם",
      "נץ",
      "עפרוני"
    ]
}
  
  
}
